MANIFEST.in
README.rst
setup.py
docs/HISTORY.txt
docs/LICENSE.GPL
docs/LICENSE.txt
eea/__init__.py
eea.alchemy.egg-info/PKG-INFO
eea.alchemy.egg-info/SOURCES.txt
eea.alchemy.egg-info/dependency_links.txt
eea.alchemy.egg-info/entry_points.txt
eea.alchemy.egg-info/namespace_packages.txt
eea.alchemy.egg-info/not-zip-safe
eea.alchemy.egg-info/requires.txt
eea.alchemy.egg-info/top_level.txt
eea/alchemy/README.txt
eea/alchemy/__init__.py
eea/alchemy/config.py
eea/alchemy/configure.zcml
eea/alchemy/interfaces.py
eea/alchemy/profiles.zcml
eea/alchemy/version.txt
eea/alchemy/browser/__init__.py
eea/alchemy/browser/configure.zcml
eea/alchemy/browser/app/__init__.py
eea/alchemy/browser/app/tool.py
eea/alchemy/browser/app/view.py
eea/alchemy/browser/app/viewlets.py
eea/alchemy/browser/css/bootstrap.css
eea/alchemy/browser/css/tool.css
eea/alchemy/browser/css/view.css
eea/alchemy/browser/js/tool.js
eea/alchemy/browser/js/view.js
eea/alchemy/browser/png/glyphicons-halflings-white.png
eea/alchemy/browser/png/glyphicons-halflings.png
eea/alchemy/browser/png/loader.gif
eea/alchemy/browser/png/tool.png
eea/alchemy/browser/zpt/search.pt
eea/alchemy/browser/zpt/tool.pt
eea/alchemy/browser/zpt/viewlet.pt
eea/alchemy/controlpanel/__init__.py
eea/alchemy/controlpanel/configure.zcml
eea/alchemy/controlpanel/interfaces.py
eea/alchemy/controlpanel/schema.py
eea/alchemy/controlpanel/settings.py
eea/alchemy/discover/__init__.py
eea/alchemy/discover/configure.zcml
eea/alchemy/discover/vocabularies.py
eea/alchemy/discover/adapters/__init__.py
eea/alchemy/discover/adapters/geotags.py
eea/alchemy/discover/adapters/keywords.py
eea/alchemy/discover/adapters/relations.py
eea/alchemy/discover/adapters/time.py
eea/alchemy/discover/utilities/__init__.py
eea/alchemy/discover/utilities/geotags.py
eea/alchemy/discover/utilities/iframes.py
eea/alchemy/discover/utilities/keywords.py
eea/alchemy/discover/utilities/links.py
eea/alchemy/discover/utilities/time.py
eea/alchemy/locales/eea.pot
eea/alchemy/locales/update.sh
eea/alchemy/locales/bg/LC_MESSAGES/eea.po
eea/alchemy/locales/cs/LC_MESSAGES/eea.po
eea/alchemy/locales/da/LC_MESSAGES/eea.po
eea/alchemy/locales/de/LC_MESSAGES/eea.po
eea/alchemy/locales/el/LC_MESSAGES/eea.po
eea/alchemy/locales/en/LC_MESSAGES/eea.po
